piquasso/cvqnn.py
piquasso/dual_rail_encoding.py
piquasso/_utils.py
piquasso/__init__.py
piquasso/api/branch.py
piquasso/api/computer.py
piquasso/api/config.py
piquasso/api/connector.py
piquasso/api/exceptions.py
piquasso/api/instruction.py
piquasso/api/mode.py
piquasso/api/program.py
piquasso/api/result.py
piquasso/api/simulator.py
piquasso/api/state.py
piquasso/api/utils.py
piquasso/api/__init__.py
piquasso/core/_blackbird.py
piquasso/core/_context.py
piquasso/core/_expressions.py
piquasso/core/_mixins.py
piquasso/core/__init__.py
piquasso/decompositions/clements.py
piquasso/decompositions/__init__.py
piquasso/fermionic/instructions.py
piquasso/fermionic/_utils.py
piquasso/fermionic/__init__.py
piquasso/fermionic/fock/simulation_steps.py
piquasso/fermionic/fock/simulator.py
piquasso/fermionic/fock/state.py
piquasso/fermionic/fock/_utils.py
piquasso/fermionic/fock/__init__.py
piquasso/fermionic/gaussian/simulation_steps.py
piquasso/fermionic/gaussian/simulator.py
piquasso/fermionic/gaussian/state.py
piquasso/fermionic/gaussian/__init__.py
piquasso/instructions/batch.py
piquasso/instructions/channels.py
piquasso/instructions/gates.py
piquasso/instructions/measurements.py
piquasso/instructions/preparations.py
piquasso/instructions/__init__.py
piquasso/_math/CMakeLists.txt
piquasso/_math/combinatorics.py
piquasso/_math/decompositions.py
piquasso/_math/fock.py
piquasso/_math/functions.py
piquasso/_math/gate_matrices.py
piquasso/_math/gradients.py
piquasso/_math/indices.py
piquasso/_math/linalg.py
piquasso/_math/permanent.cp39-win_amd64.pyd
piquasso/_math/permanent.cpp
piquasso/_math/pfaffian.cp39-win_amd64.pyd
piquasso/_math/pfaffian.cpp
piquasso/_math/symplectic.py
piquasso/_math/torontonian.cp39-win_amd64.pyd
piquasso/_math/torontonian.cpp
piquasso/_math/transformations.py
piquasso/_math/validations.py
piquasso/_math/_random.py
piquasso/_math/__init__.py
piquasso/_math/hafnian/hessenberg.py
piquasso/_math/hafnian/labudde.py
piquasso/_math/hafnian/loop_corrections.py
piquasso-7.1.0.dist-info/DELVEWHEEL
piquasso-7.1.0.dist-info/METADATA
piquasso-7.1.0.dist-info/RECORD
piquasso-7.1.0.dist-info/WHEEL
piquasso-7.1.0.dist-info/licenses/LICENSE.txt
