Metadata-Version: 2.2
Name: piquasso
Version: 7.1.0
Summary: A Photonic Quantum Computer Simulator written in Python and C++.
Keywords: quantum computing,photonic quantum computing,boson sampling
Maintainer-Email: Budapest Quantum Computing Group <kolarovszki@inf.elte.hu>
License: 
Classifier: Intended Audience :: Science/Research
Classifier: License :: OSI Approved :: Apache Software License
Classifier: Natural Language :: English
Classifier: Programming Language :: C++
Classifier: Programming Language :: Python :: 3
Classifier: Programming Language :: Python :: 3.8
Classifier: Programming Language :: Python :: 3.9
Classifier: Programming Language :: Python :: 3.10
Classifier: Programming Language :: Python :: 3.11
Classifier: Programming Language :: Python :: 3.12
Classifier: Topic :: Scientific/Engineering :: Quantum Computing
Classifier: Development Status :: 5 - Production/Stable
Project-URL: Homepage, https://piquasso.com
Project-URL: Documentation, https://piquasso.readthedocs.io
Project-URL: Repository, https://github.com/Budapest-Quantum-Computing-Group/piquasso
Project-URL: Issues, https://github.com/Budapest-Quantum-Computing-Group/piquasso/issues
Project-URL: Changelog, https://github.com/Budapest-Quantum-Computing-Group/piquasso/blob/main/CHANGELOG.md
Requires-Python: <3.14,>=3.8
Requires-Dist: numpy>=1.19.5
Requires-Dist: scipy>=1.5.4
Requires-Dist: numba>=0.57.1
Requires-Dist: quantum-blackbird==0.5.0
Provides-Extra: qiskit
Requires-Dist: qiskit; extra == "qiskit"
Provides-Extra: tensorflow
Requires-Dist: tensorflow; extra == "tensorflow"
Provides-Extra: jax
Requires-Dist: jax[cpu]; extra == "jax"
Provides-Extra: matplotlib
Requires-Dist: matplotlib; extra == "matplotlib"
Provides-Extra: dask
Requires-Dist: dask; extra == "dask"
Provides-Extra: dev
Requires-Dist: pytest<8.5.0,>=8.0.1; extra == "dev"
Requires-Dist: coverage<7.11.0,>=7.6.1; extra == "dev"
Requires-Dist: mypy==1.8.0; extra == "dev"
Requires-Dist: flake8<7.4.0,>=7.1.1; extra == "dev"
Requires-Dist: nbqa<1.10.0,>=1.3.1; extra == "dev"
Requires-Dist: nbmake~=1.5.4; extra == "dev"
Requires-Dist: black<25.10,>=24.2; extra == "dev"
Requires-Dist: pytest-lazy-fixtures==1.4.0; extra == "dev"
Provides-Extra: docs
Requires-Dist: sphinx<8.3.0,>=7.1.2; extra == "docs"
Requires-Dist: nbsphinx~=0.9.5; extra == "docs"
Requires-Dist: furo<2025.10.0,>=2024.8.6; extra == "docs"
Requires-Dist: ipython<9.1.0,>=8.12.3; extra == "docs"
Requires-Dist: sphinx-copybutton~=0.5.2; extra == "docs"
Requires-Dist: sphinx-design<0.7,>=0.5; extra == "docs"
Requires-Dist: sphinxcontrib-bibtex==2.6.5; extra == "docs"
Provides-Extra: benchmark
Requires-Dist: matplotlib<3.11.0,>=3.9.2; extra == "benchmark"
Requires-Dist: pytest-profiling<1.9,>=1.7; extra == "benchmark"
Requires-Dist: pytest-benchmark<5.3,>=4.0; extra == "benchmark"
Requires-Dist: perceval-quandela<1.1.0,>=0.11.2; extra == "benchmark"
